pinnicle/__init__.py
pinnicle/parameter.py
pinnicle/pinn.py
pinnicle/domain/__init__.py
pinnicle/domain/domain.py
pinnicle/modeldata/__init__.py
pinnicle/modeldata/data.py
pinnicle/modeldata/general_mat_data.py
pinnicle/modeldata/h5_data.py
pinnicle/modeldata/issm_data.py
pinnicle/modeldata/issm_light.py
pinnicle/modeldata/netcdf_data.py
pinnicle/nn/__init__.py
pinnicle/nn/helper.py
pinnicle/nn/nn.py
pinnicle/physics/__init__.py
pinnicle/physics/constants.py
pinnicle/physics/continuity.py
pinnicle/physics/dummy.py
pinnicle/physics/equationbase.py
pinnicle/physics/friction.py
pinnicle/physics/iceshelf.py
pinnicle/physics/physics.py
pinnicle/physics/stressbalance.py
pinnicle/physics/timeinvariant.py
pinnicle/utils/__init__.py
pinnicle/utils/backends_specified.py
pinnicle/utils/data_misfit.py
pinnicle/utils/helper.py
pinnicle/utils/history.py
pinnicle/utils/plotting.py
pinnicle-1.1.dist-info/licenses/LICENSE
tests/.coverage
tests/__init__.py
tests/test_data.py
tests/test_domain.py
tests/test_nn.py
tests/test_parameters.py
tests/test_pde.py
tests/test_physics.py
tests/test_pinn.py
tests/test_plotting.py
tests/test_utils.py
pinnicle-1.1.dist-info/METADATA
pinnicle-1.1.dist-info/WHEEL
pinnicle-1.1.dist-info/top_level.txt
pinnicle-1.1.dist-info/RECORD
