Metadata-Version: 2.4
Name: PINNICLE
Version: 1.1
Summary: A Python library for solving ice sheet modeling problems using Physics Informed Neural Networks
Author-email: Cheng Gong <gong.cheng@dartmouth.edu>, Mansa Krishna <mansa.krishna.gr@dartmouth.edu>, Mathieu Morlighem <Mathieu.Morlighem@dartmouth.edu>
Project-URL: Homepage, https://github.com/ISSMteam/PINNICLE
Project-URL: Documentation, https://pinnicle.readthedocs.io
Project-URL: Bug Tracker, https://github.com/ISSMteam/PINNICLE/issues
Keywords: Ice sheet modeling,Numerical method,Deep learning,Physics-informed neural networks
Classifier: Development Status :: 3 - Alpha
Classifier: Intended Audience :: Science/Research
Classifier: License :: OSI Approved :: GNU Lesser General Public License v2 (LGPLv2)
Classifier: Programming Language :: Python :: 3
Classifier: Programming Language :: Python :: 3.9
Classifier: Programming Language :: Python :: 3.10
Classifier: Programming Language :: Python :: 3.11
Classifier: Programming Language :: Python :: 3.12
Requires-Python: >=3.9
License-File: LICENSE
Requires-Dist: numpy
Requires-Dist: scipy
Requires-Dist: scikit-learn
Requires-Dist: tensorflow>=2.11.0
Requires-Dist: tensorflow-probability[tf]>=0.19.0
Requires-Dist: matplotlib
Requires-Dist: pandas
Requires-Dist: mat73
Requires-Dist: deepxde
Dynamic: license-file
